discere/__init__.py
discere/discere.py
discere/features/__init__.py
discere/features/feature_extraction.py
discere/features/config/attrib
discere/preprocessing/__init__.py
discere/preprocessing/process_fasta.py
discere-0.0.4.dist-info/LICENSE.txt
discere-0.0.4.dist-info/METADATA
discere-0.0.4.dist-info/WHEEL
discere-0.0.4.dist-info/top_level.txt
discere-0.0.4.dist-info/RECORD
