Metadata-Version: 2.1
Name: discere
Version: 0.0.4
Summary: Protein Feature Extraction package for Machine Learning
Home-page: https://github.com/jithin8mathew/Protein-feature-extraction
Author: Jithin Mathew
Author-email: jithinjm1995@gmail.com
License: MIT
Keywords: feature extraction protein sequence bioinformatics machine learning deep learning
Platform: any
Classifier: License :: OSI Approved :: MIT License
Classifier: Programming Language :: Python
Classifier: Programming Language :: Python :: 3.5
Classifier: Programming Language :: Python :: 3.6
Classifier: Programming Language :: Python :: 3.7
Classifier: Programming Language :: Python :: 3.8
Classifier: Topic :: Software Development :: Libraries
Classifier: Topic :: Software Development :: Libraries :: Python Modules
Classifier: Intended Audience :: Developers
Classifier: Intended Audience :: Education
Classifier: Operating System :: OS Independent
Requires-Dist: pandas
Requires-Dist: biopython
